docpose/__init__.py
docpose/main.py
libs/__init__.py
libs/challenge_env.py
libs/check_file_exists.py
libs/compose_item_validator.py
libs/config_classes.py
libs/constants.py
libs/create_args.py
libs/custom_exceptions.py
libs/dict_to_dataclass.py
libs/get_envs_to_template.py
libs/get_templates.py
libs/jinja2_extend_filters.py
libs/parse_env_file.py
libs/prepare_env_variables.py
libs/process_templates.py
libs/read_config_yml.py
libs/render_templates.py
libs/store.py
libs/validate_config_compose.py
libs/validate_config_source.py
libs/write_to_path.py
docpose-1.2.10.dist-info/LICENSE
docpose-1.2.10.dist-info/METADATA
docpose-1.2.10.dist-info/WHEEL
docpose-1.2.10.dist-info/entry_points.txt
docpose-1.2.10.dist-info/RECORD
