Metadata-Version: 2.1
Name: docpose
Version: 1.2.10
Summary: A small templating engine using a .docpose.yml file for generating documents
License: MIT
Author: Eugen Hildt
Author-email: eugen.hildt@gmail.com
Requires-Python: >=3.10,<3.13
Classifier: License :: OSI Approved :: MIT License
Classifier: Programming Language :: Python :: 3
Classifier: Programming Language :: Python :: 3.10
Classifier: Programming Language :: Python :: 3.11
Classifier: Programming Language :: Python :: 3.12
Requires-Dist: colorama (>=0.4.6,<0.5.0)
Requires-Dist: jinja2 (>=3.1.4,<4.0.0)
Requires-Dist: pyyaml (>=6.0.1,<7.0.0)
